{"nodes": [{"id": "c_users_min21_desktop_flutter_grame_flutter_game_lib_game_components_projectiles_base_projectile_dart", "label": "base_projectile.dart", "file_type": "code", "source_file": "C:\\Users\\min21\\Desktop\\flutter_grame\\flutter_game\\lib\\game\\components\\projectiles\\base_projectile.dart", "source_location": null}, {"id": "c_users_min21_desktop_flutter_grame_flutter_game_lib_game_components_projectiles_base_projectile_dart_projectile", "label": "Projectile", "file_type": "code", "source_file": "C:\\Users\\min21\\Desktop\\flutter_grame\\flutter_game\\lib\\game\\components\\projectiles\\base_projectile.dart", "source_location": null}, {"id": "c_users_min21_desktop_flutter_grame_flutter_game_lib_game_components_projectiles_base_projectile_dart_tagcomponent", "label": "TagComponent", "file_type": "code", "source_file": "C:\\Users\\min21\\Desktop\\flutter_grame\\flutter_game\\lib\\game\\components\\projectiles\\base_projectile.dart", "source_location": null}, {"id": "c_users_min21_desktop_flutter_grame_flutter_game_lib_game_components_projectiles_base_projectile_dart_resolvepaintcolor", "label": "_resolvePaintColor", "file_type": "code", "source_file": "C:\\Users\\min21\\Desktop\\flutter_grame\\flutter_game\\lib\\game\\components\\projectiles\\base_projectile.dart", "source_location": null}, {"id": "c_users_min21_desktop_flutter_grame_flutter_game_lib_game_components_projectiles_base_projectile_dart_color", "label": "Color", "file_type": "code", "source_file": "C:\\Users\\min21\\Desktop\\flutter_grame\\flutter_game\\lib\\game\\components\\projectiles\\base_projectile.dart", "source_location": null}, {"id": "c_users_min21_desktop_flutter_grame_flutter_game_lib_game_components_projectiles_base_projectile_dart_onmount", "label": "onMount", "file_type": "code", "source_file": "C:\\Users\\min21\\Desktop\\flutter_grame\\flutter_game\\lib\\game\\components\\projectiles\\base_projectile.dart", "source_location": null}, {"id": "c_users_min21_desktop_flutter_grame_flutter_game_lib_game_components_projectiles_base_projectile_dart_onremove", "label": "onRemove", "file_type": "code", "source_file": "C:\\Users\\min21\\Desktop\\flutter_grame\\flutter_game\\lib\\game\\components\\projectiles\\base_projectile.dart", "source_location": null}, {"id": "c_users_min21_desktop_flutter_grame_flutter_game_lib_game_components_projectiles_base_projectile_dart_update", "label": "update", "file_type": "code", "source_file": "C:\\Users\\min21\\Desktop\\flutter_grame\\flutter_game\\lib\\game\\components\\projectiles\\base_projectile.dart", "source_location": null}, {"id": "c_users_min21_desktop_flutter_grame_flutter_game_lib_game_components_projectiles_base_projectile_dart_triggersplashandremove", "label": "_triggerSplashAndRemove", "file_type": "code", "source_file": "C:\\Users\\min21\\Desktop\\flutter_grame\\flutter_game\\lib\\game\\components\\projectiles\\base_projectile.dart", "source_location": null}, {"id": "c_users_min21_desktop_flutter_grame_flutter_game_lib_game_components_projectiles_base_projectile_dart_oncollisionstart", "label": "onCollisionStart", "file_type": "code", "source_file": "C:\\Users\\min21\\Desktop\\flutter_grame\\flutter_game\\lib\\game\\components\\projectiles\\base_projectile.dart", "source_location": null}, {"id": "package_flame_collisions_dart", "label": "package:flame/collisions.dart", "file_type": "code", "source_file": "C:\\Users\\min21\\Desktop\\flutter_grame\\flutter_game\\lib\\game\\components\\projectiles\\base_projectile.dart", "source_location": null}, {"id": "package_flame_components_dart", "label": "package:flame/components.dart", "file_type": "code", "source_file": "C:\\Users\\min21\\Desktop\\flutter_grame\\flutter_game\\lib\\game\\components\\projectiles\\base_projectile.dart", "source_location": null}, {"id": "package_flutter_material_dart", "label": "package:flutter/material.dart", "file_type": "code", "source_file": "C:\\Users\\min21\\Desktop\\flutter_grame\\flutter_game\\lib\\game\\components\\projectiles\\base_projectile.dart", "source_location": null}, {"id": "mbti_game_dart", "label": "../../mbti_game.dart", "file_type": "code", "source_file": "C:\\Users\\min21\\Desktop\\flutter_grame\\flutter_game\\lib\\game\\components\\projectiles\\base_projectile.dart", "source_location": null}, {"id": "enemies_base_enemy_dart", "label": "../enemies/base_enemy.dart", "file_type": "code", "source_file": "C:\\Users\\min21\\Desktop\\flutter_grame\\flutter_game\\lib\\game\\components\\projectiles\\base_projectile.dart", "source_location": null}, {"id": "player_dart", "label": "../player.dart", "file_type": "code", "source_file": "C:\\Users\\min21\\Desktop\\flutter_grame\\flutter_game\\lib\\game\\components\\projectiles\\base_projectile.dart", "source_location": null}], "edges": [{"source": "c_users_min21_desktop_flutter_grame_flutter_game_lib_game_components_projectiles_base_projectile_dart", "target": "c_users_min21_desktop_flutter_grame_flutter_game_lib_game_components_projectiles_base_projectile_dart_projectile", "relation": "defines", "confidence": "EXTRACTED", "confidence_score": 1.0, "source_file": "C:\\Users\\min21\\Desktop\\flutter_grame\\flutter_game\\lib\\game\\components\\projectiles\\base_projectile.dart", "source_location": null, "weight": 1.0}, {"source": "c_users_min21_desktop_flutter_grame_flutter_game_lib_game_components_projectiles_base_projectile_dart", "target": "c_users_min21_desktop_flutter_grame_flutter_game_lib_game_components_projectiles_base_projectile_dart_tagcomponent", "relation": "defines", "confidence": "EXTRACTED", "confidence_score": 1.0, "source_file": "C:\\Users\\min21\\Desktop\\flutter_grame\\flutter_game\\lib\\game\\components\\projectiles\\base_projectile.dart", "source_location": null, "weight": 1.0}, {"source": "c_users_min21_desktop_flutter_grame_flutter_game_lib_game_components_projectiles_base_projectile_dart", "target": "c_users_min21_desktop_flutter_grame_flutter_game_lib_game_components_projectiles_base_projectile_dart_resolvepaintcolor", "relation": "defines", "confidence": "EXTRACTED", "confidence_score": 1.0, "source_file": "C:\\Users\\min21\\Desktop\\flutter_grame\\flutter_game\\lib\\game\\components\\projectiles\\base_projectile.dart", "source_location": null, "weight": 1.0}, {"source": "c_users_min21_desktop_flutter_grame_flutter_game_lib_game_components_projectiles_base_projectile_dart", "target": "c_users_min21_desktop_flutter_grame_flutter_game_lib_game_components_projectiles_base_projectile_dart_color", "relation": "defines", "confidence": "EXTRACTED", "confidence_score": 1.0, "source_file": "C:\\Users\\min21\\Desktop\\flutter_grame\\flutter_game\\lib\\game\\components\\projectiles\\base_projectile.dart", "source_location": null, "weight": 1.0}, {"source": "c_users_min21_desktop_flutter_grame_flutter_game_lib_game_components_projectiles_base_projectile_dart", "target": "c_users_min21_desktop_flutter_grame_flutter_game_lib_game_components_projectiles_base_projectile_dart_onmount", "relation": "defines", "confidence": "EXTRACTED", "confidence_score": 1.0, "source_file": "C:\\Users\\min21\\Desktop\\flutter_grame\\flutter_game\\lib\\game\\components\\projectiles\\base_projectile.dart", "source_location": null, "weight": 1.0}, {"source": "c_users_min21_desktop_flutter_grame_flutter_game_lib_game_components_projectiles_base_projectile_dart", "target": "c_users_min21_desktop_flutter_grame_flutter_game_lib_game_components_projectiles_base_projectile_dart_onremove", "relation": "defines", "confidence": "EXTRACTED", "confidence_score": 1.0, "source_file": "C:\\Users\\min21\\Desktop\\flutter_grame\\flutter_game\\lib\\game\\components\\projectiles\\base_projectile.dart", "source_location": null, "weight": 1.0}, {"source": "c_users_min21_desktop_flutter_grame_flutter_game_lib_game_components_projectiles_base_projectile_dart", "target": "c_users_min21_desktop_flutter_grame_flutter_game_lib_game_components_projectiles_base_projectile_dart_update", "relation": "defines", "confidence": "EXTRACTED", "confidence_score": 1.0, "source_file": "C:\\Users\\min21\\Desktop\\flutter_grame\\flutter_game\\lib\\game\\components\\projectiles\\base_projectile.dart", "source_location": null, "weight": 1.0}, {"source": "c_users_min21_desktop_flutter_grame_flutter_game_lib_game_components_projectiles_base_projectile_dart", "target": "c_users_min21_desktop_flutter_grame_flutter_game_lib_game_components_projectiles_base_projectile_dart_triggersplashandremove", "relation": "defines", "confidence": "EXTRACTED", "confidence_score": 1.0, "source_file": "C:\\Users\\min21\\Desktop\\flutter_grame\\flutter_game\\lib\\game\\components\\projectiles\\base_projectile.dart", "source_location": null, "weight": 1.0}, {"source": "c_users_min21_desktop_flutter_grame_flutter_game_lib_game_components_projectiles_base_projectile_dart", "target": "c_users_min21_desktop_flutter_grame_flutter_game_lib_game_components_projectiles_base_projectile_dart_oncollisionstart", "relation": "defines", "confidence": "EXTRACTED", "confidence_score": 1.0, "source_file": "C:\\Users\\min21\\Desktop\\flutter_grame\\flutter_game\\lib\\game\\components\\projectiles\\base_projectile.dart", "source_location": null, "weight": 1.0}, {"source": "c_users_min21_desktop_flutter_grame_flutter_game_lib_game_components_projectiles_base_projectile_dart", "target": "package_flame_collisions_dart", "relation": "imports", "confidence": "EXTRACTED", "confidence_score": 1.0, "source_file": "C:\\Users\\min21\\Desktop\\flutter_grame\\flutter_game\\lib\\game\\components\\projectiles\\base_projectile.dart", "source_location": null, "weight": 1.0}, {"source": "c_users_min21_desktop_flutter_grame_flutter_game_lib_game_components_projectiles_base_projectile_dart", "target": "package_flame_components_dart", "relation": "imports", "confidence": "EXTRACTED", "confidence_score": 1.0, "source_file": "C:\\Users\\min21\\Desktop\\flutter_grame\\flutter_game\\lib\\game\\components\\projectiles\\base_projectile.dart", "source_location": null, "weight": 1.0}, {"source": "c_users_min21_desktop_flutter_grame_flutter_game_lib_game_components_projectiles_base_projectile_dart", "target": "package_flutter_material_dart", "relation": "imports", "confidence": "EXTRACTED", "confidence_score": 1.0, "source_file": "C:\\Users\\min21\\Desktop\\flutter_grame\\flutter_game\\lib\\game\\components\\projectiles\\base_projectile.dart", "source_location": null, "weight": 1.0}, {"source": "c_users_min21_desktop_flutter_grame_flutter_game_lib_game_components_projectiles_base_projectile_dart", "target": "mbti_game_dart", "relation": "imports", "confidence": "EXTRACTED", "confidence_score": 1.0, "source_file": "C:\\Users\\min21\\Desktop\\flutter_grame\\flutter_game\\lib\\game\\components\\projectiles\\base_projectile.dart", "source_location": null, "weight": 1.0}, {"source": "c_users_min21_desktop_flutter_grame_flutter_game_lib_game_components_projectiles_base_projectile_dart", "target": "enemies_base_enemy_dart", "relation": "imports", "confidence": "EXTRACTED", "confidence_score": 1.0, "source_file": "C:\\Users\\min21\\Desktop\\flutter_grame\\flutter_game\\lib\\game\\components\\projectiles\\base_projectile.dart", "source_location": null, "weight": 1.0}, {"source": "c_users_min21_desktop_flutter_grame_flutter_game_lib_game_components_projectiles_base_projectile_dart", "target": "player_dart", "relation": "imports", "confidence": "EXTRACTED", "confidence_score": 1.0, "source_file": "C:\\Users\\min21\\Desktop\\flutter_grame\\flutter_game\\lib\\game\\components\\projectiles\\base_projectile.dart", "source_location": null, "weight": 1.0}]}